LICENSE
README.md
setup.py
etacad/__init__.py
etacad/bar.py
etacad/beam.py
etacad/cadtable.py
etacad/column.py
etacad/concrete.py
etacad/converters.py
etacad/drawing_utils.py
etacad/element.py
etacad/errors.py
etacad/footing.py
etacad/globals.py
etacad/slab.py
etacad/spaced_bars.py
etacad/stirrup.py
etacad/utils.py
etacad.egg-info/PKG-INFO
etacad.egg-info/SOURCES.txt
etacad.egg-info/dependency_links.txt
etacad.egg-info/requires.txt
etacad.egg-info/top_level.txt
etacad/geometry/__init__.py
etacad/geometry/polygon.py
etacad/geometry/utils.py
tests/__init__.py
tests/test_bar.py
tests/test_beam.py
tests/test_cadtable.py
tests/test_column.py
tests/test_concrete.py
tests/test_slab.py
tests/test_spaced_bars.py
tests/geometry/__init__.py
tests/geometry/test_polygon.py