Metadata-Version: 2.1
Name: etacad
Version: 0.0.14
Summary: A package aimed to simpilfy drawings of structurals elements based on ezdxf library.
Home-page: https://github.com/AxelTAG/etacad.git
Author: Kevin Axel Tagliaferri
Author-email: kevinaxeltagliaferri@hotmail.com
License-File: LICENSE
Requires-Dist: attrs
Requires-Dist: ezdxf
